dict_pretty_printer/__init__.py
dict_pretty_printer-0.2.dist-info/LICENSE
dict_pretty_printer-0.2.dist-info/METADATA
dict_pretty_printer-0.2.dist-info/WHEEL
dict_pretty_printer-0.2.dist-info/top_level.txt
dict_pretty_printer-0.2.dist-info/RECORD
