Metadata-Version: 2.1
Name: dict-pretty-printer
Version: 0.2
Summary: a good description for dict pretty printer
Home-page: https://github.com/JackonYang/dict-pretty-printer
Author: Jackon Yang
Author-email: i@jackon.me
License: MIT
Platform: UNKNOWN
